globy_apm/__init__.py
globy_apm/client.py
globy_apm/interfaces.py
globy_apm/backends/openpanel.py
globy_apm-0.1.0.dist-info/METADATA
globy_apm-0.1.0.dist-info/WHEEL
globy_apm-0.1.0.dist-info/top_level.txt
globy_apm-0.1.0.dist-info/RECORD
