Metadata-Version: 2.4
Name: globy-apm
Version: 0.1.0
Summary: A minimal, async, typed APM package for Python 3.13+
Author-email: Globy Team <team@globy.com>
License: MIT
Classifier: Programming Language :: Python :: 3
Classifier: Programming Language :: Python :: 3.13
Classifier: Typing :: Typed
Requires-Python: >=3.13
Requires-Dist: openpanel
Provides-Extra: dev
Requires-Dist: pylint; extra == "dev"
Requires-Dist: pytest; extra == "dev"
Requires-Dist: mypy; extra == "dev"
Requires-Dist: types-requests; extra == "dev"
